giacpy/GPL-2
giacpy/__init__.py
giacpy/giacpy.cp312-win_amd64.pyd
giacpy/giacpy.pyi
giacpy/giacxcas.dll
giacpy/libao-4.dll
giacpy/libblas.dll
giacpy/libbrotlicommon.dll
giacpy/libbrotlidec.dll
giacpy/libcrypto-1_1-x64.dll
giacpy/libcurl-4.dll
giacpy/libdl.dll
giacpy/libfltk.dll
giacpy/libfltk_forms.dll
giacpy/libfltk_gl.dll
giacpy/libfltk_images.dll
giacpy/libgcc_s_seh-1.dll
giacpy/libgfortran-5.dll
giacpy/libglpk-40.dll
giacpy/libgmp-10.dll
giacpy/libgsl-27.dll
giacpy/libgslcblas-0.dll
giacpy/libiconv-2.dll
giacpy/libidn2-0.dll
giacpy/libintl-8.dll
giacpy/libjpeg-8.dll
giacpy/liblapack.dll
giacpy/libnghttp2-14.dll
giacpy/libpng16-16.dll
giacpy/libpsl-5.dll
giacpy/libquadmath-0.dll
giacpy/libreadline8.dll
giacpy/libsamplerate-0.dll
giacpy/libssh2-1.dll
giacpy/libssl-1_1-x64.dll
giacpy/libssp-0.dll
giacpy/libstdc++-6.dll
giacpy/libtermcap-0.dll
giacpy/libunistring-2.dll
giacpy/libusb-1.0.dll
giacpy/libwinpthread-1.dll
giacpy/libzstd.dll
giacpy/mgwfltknox-1.3.dll
giacpy/mgwfltknox_gl-1.3.dll
giacpy/mgwfltknox_images-1.3.dll
giacpy/msys-2.0.dll
giacpy/zlib1.dll
giacpy-0.7.5.dist-info/METADATA
giacpy-0.7.5.dist-info/WHEEL
giacpy-0.7.5.dist-info/top_level.txt
giacpy-0.7.5.dist-info/RECORD
