Metadata-Version: 2.1
Name: giacpy
Version: 0.7.5
Summary: A Cython frontend to the c++ library giac. (Computer Algebra System)
Home-page: http://www.imj-prg.fr/~frederic.han/xcas/giacpy/
Author: Frederic Han
Author-email: frederic.han@imj-prg.fr
License: GPLv2 or above
